xarray_safeguards/__init__.py
xarray_safeguards/py.typed
xarray_safeguards-0.1.0b1.dist-info/METADATA
xarray_safeguards-0.1.0b1.dist-info/WHEEL
xarray_safeguards-0.1.0b1.dist-info/licenses/LICENSE
xarray_safeguards-0.1.0b1.dist-info/RECORD
